{
  "status": "success",
  "data": {
    "resultType": "matrix",
    "result": [
      {
        "metric": {
          "__name__": "app_resource_assign_ratio",
          "app": "App1",
          "rp": "huchi1",
          "tenant": "IT",
          "type": "BM"
        },
        "values": [
          [1604472782.033,"86.66666666666667"],
          [1604473382.033,"55"],
          [1604473982.033,"95"],
          [1604474582.033,"91.66666666666667"],
          [1604475182.033,"56.666666666666664"],
          [1604475782.033,"56.666666666666664"],
          [1604476382.033,"58.333333333333336"]]
      },
      {
        "metric": {
          "__name__": "app_resource_assign_ratio",
          "app": "App1",
          "rp": "huchi1",
          "tenant": "IT",
          "type": "MEM"
        },
        "values": [
          [1604472782.033,"66.66666666666667"],
          [1604473382.033,"35"],
          [1604473982.033,"75"],
          [1604474582.033,"71.66666666666667"],
          [1604475182.033,"36.666666666666664"],
          [1604475782.033,"36.666666666666664"],
          [1604476382.033,"38.333333333333336"]]
      },
      {
        "metric": {
          "__name__": "app_resource_assign_ratio",
          "app": "App1",
          "rp": "huchi1",
          "tenant": "IT",
          "type": "VCPU"
        },
        "values": [
          [1604472782.033,"56.66666666666667"],
          [1604473382.033,"25"],
          [1604473982.033,"65"],
          [1604474582.033,"61.66666666666667"],
          [1604475182.033,"26.666666666666664"],
          [1604475782.033,"26.666666666666664"],
          [1604476382.033,"28.333333333333336"]]
      },
      {
        "metric": {
          "__name__": "app_resource_assign_ratio",
          "app": "App1",
          "rp": "huchi1",
          "tenant": "IT",
          "type": "VM"
        },
        "values": [
          [1604472782.033,"46.66666666666667"],
          [1604473382.033,"15"],
          [1604473982.033,"15"],
          [1604474582.033,"51.66666666666667"],
          [1604475182.033,"16.666666666666664"],
          [1604475782.033,"16.666666666666664"],
          [1604476382.033,"8.333333333333336"]]
      }
    ]
  }
}
